_fib.abi3.so
simplefibcffi.py
simplefibcffi-0.3.dist-info/METADATA
simplefibcffi-0.3.dist-info/top_level.txt
simplefibcffi-0.3.dist-info/RECORD
simplefibcffi-0.3.dist-info/WHEEL
simplefibcffi-0.3.dist-info/LICENSE
